{"nodes": [{"name": "TM9SF3", "value": 35.16749108729376}, {"name": "SLC35B2", "value": 75.38721614328027}, {"name": "MAN1B1", "value": 70.52287874528034}, {"name": "TM9SF4", "value": 63.420216403383186}, {"name": "TM9SF2", "value": 76.18708664335715}, {"name": "SLC35A2", "value": 59.72124639904717}, {"name": "RABAC1", "value": 39.619788758288394}, {"name": "GOLGB1", "value": 38.494850021680094}, {"name": "CASC4", "value": 43.18708664335715}], "edges": [{"source": "TM9SF4", "target": "SLC35B2"}, {"source": "TM9SF2", "target": "CASC4"}, {"source": "TM9SF2", "target": "MAN1B1"}, {"source": "SLC35A2", "target": "SLC35B2"}, {"source": "SLC35A2", "target": "GOLGB1"}, {"source": "TM9SF4", "target": "CASC4"}, {"source": "TM9SF3", "target": "RABAC1"}, {"source": "TM9SF4", "target": "MAN1B1"}, {"source": "TM9SF4", "target": "SLC35A2"}, {"source": "SLC35A2", "target": "CASC4"}, {"source": "TM9SF3", "target": "TM9SF2"}, {"source": "SLC35A2", "target": "MAN1B1"}, {"source": "CASC4", "target": "GOLGB1"}, {"source": "RABAC1", "target": "SLC35B2"}, {"source": "GOLGB1", "target": "MAN1B1"}, {"source": "SLC35B2", "target": "CASC4"}, {"source": "TM9SF4", "target": "GOLGB1"}, {"source": "SLC35B2", "target": "MAN1B1"}, {"source": "RABAC1", "target": "GOLGB1"}, {"source": "TM9SF4", "target": "RABAC1"}, {"source": "TM9SF3", "target": "SLC35B2"}, {"source": "CASC4", "target": "MAN1B1"}, {"source": "TM9SF3", "target": "TM9SF4"}, {"source": "TM9SF3", "target": "GOLGB1"}, {"source": "RABAC1", "target": "CASC4"}, {"source": "RABAC1", "target": "MAN1B1"}, {"source": "TM9SF4", "target": "TM9SF2"}, {"source": "RABAC1", "target": "TM9SF2"}, {"source": "SLC35A2", "target": "RABAC1"}, {"source": "SLC35B2", "target": "GOLGB1"}, {"source": "TM9SF2", "target": "SLC35B2"}, {"source": "TM9SF2", "target": "GOLGB1"}, {"source": "TM9SF3", "target": "CASC4"}, {"source": "SLC35A2", "target": "TM9SF2"}, {"source": "TM9SF3", "target": "MAN1B1"}, {"source": "TM9SF3", "target": "SLC35A2"}]}