{"nodes": [{"name": "MRPL46", "value": 3.537602002101044}, {"name": "HSPD1", "value": 31.30102999566398}, {"name": "WARS2", "value": -8.67778070526608}, {"name": "PNPT1", "value": 20.55284196865778}, {"name": "TRAP1", "value": 1.494850021680094}, {"name": "MCAT", "value": -0.08618614761628333}, {"name": "NDUFAF7", "value": -5.886056647693163}, {"name": "GFM2", "value": -5.795880017344075}, {"name": "MARS2", "value": -19.638272163982407}], "edges": [{"source": "NDUFAF7", "target": "MRPL46"}, {"source": "PNPT1", "target": "MRPL46"}, {"source": "TRAP1", "target": "GFM2"}, {"source": "HSPD1", "target": "GFM2"}, {"source": "NDUFAF7", "target": "WARS2"}, {"source": "MARS2", "target": "MRPL46"}, {"source": "TRAP1", "target": "MRPL46"}, {"source": "PNPT1", "target": "HSPD1"}, {"source": "WARS2", "target": "PNPT1"}, {"source": "MCAT", "target": "TRAP1"}, {"source": "NDUFAF7", "target": "TRAP1"}, {"source": "TRAP1", "target": "HSPD1"}, {"source": "MCAT", "target": "WARS2"}, {"source": "GFM2", "target": "MRPL46"}, {"source": "WARS2", "target": "MRPL46"}, {"source": "WARS2", "target": "TRAP1"}, {"source": "NDUFAF7", "target": "MCAT"}, {"source": "MCAT", "target": "MARS2"}, {"source": "MCAT", "target": "PNPT1"}, {"source": "HSPD1", "target": "MRPL46"}, {"source": "MCAT", "target": "HSPD1"}, {"source": "NDUFAF7", "target": "MARS2"}, {"source": "PNPT1", "target": "MARS2"}, {"source": "NDUFAF7", "target": "PNPT1"}, {"source": "NDUFAF7", "target": "HSPD1"}, {"source": "MCAT", "target": "GFM2"}, {"source": "NDUFAF7", "target": "GFM2"}, {"source": "GFM2", "target": "MARS2"}, {"source": "PNPT1", "target": "GFM2"}, {"source": "WARS2", "target": "MARS2"}, {"source": "WARS2", "target": "HSPD1"}, {"source": "TRAP1", "target": "MARS2"}, {"source": "MCAT", "target": "MRPL46"}, {"source": "WARS2", "target": "GFM2"}, {"source": "HSPD1", "target": "MARS2"}, {"source": "TRAP1", "target": "PNPT1"}]}