{"nodes": [{"name": "ITGAV", "value": 26.585026652029182}, {"name": "ITGB1", "value": -2.408935392973501}, {"name": "ITGA3", "value": -14.698970004336019}, {"name": "LAMC2", "value": 2.070581074285707}, {"name": "ITGB6", "value": 0.3279021420642826}], "edges": [{"source": "LAMC2", "target": "ITGB6"}, {"source": "ITGA3", "target": "ITGAV"}, {"source": "ITGAV", "target": "ITGB1"}, {"source": "LAMC2", "target": "ITGB1"}, {"source": "ITGB6", "target": "ITGB1"}, {"source": "ITGA3", "target": "ITGB6"}, {"source": "ITGA3", "target": "ITGB1"}, {"source": "ITGA3", "target": "LAMC2"}, {"source": "LAMC2", "target": "ITGAV"}, {"source": "ITGB6", "target": "ITGAV"}]}