{"nodes": [{"name": "HBD", "value": -52.36653154442041}, {"name": "MMRN1", "value": -68.88605664769317}, {"name": "ANK1", "value": -48.56863623584101}, {"name": "GP1BB", "value": -55.09151498112135}, {"name": "FGG", "value": -25.69897000433602}, {"name": "PPBP", "value": -90.22914798835785}, {"name": "ITGB3", "value": -32.74472749489669}, {"name": "PF4", "value": -54.431798275933005}, {"name": "TUBB1", "value": -61.01772876696043}, {"name": "ITGA2B", "value": -46.36653154442041}, {"name": "GP1BA", "value": -59.356547323513816}], "edges": [{"source": "GP1BB", "target": "HBD"}, {"source": "PF4", "target": "FGG"}, {"source": "ANK1", "target": "PF4"}, {"source": "PPBP", "target": "PF4"}, {"source": "ANK1", "target": "GP1BB"}, {"source": "GP1BB", "target": "ITGB3"}, {"source": "ITGA2B", "target": "TUBB1"}, {"source": "TUBB1", "target": "PPBP"}, {"source": "ITGA2B", "target": "PF4"}, {"source": "PF4", "target": "GP1BB"}, {"source": "MMRN1", "target": "PPBP"}, {"source": "FGG", "target": "GP1BB"}, {"source": "TUBB1", "target": "FGG"}, {"source": "ANK1", "target": "HBD"}, {"source": "PPBP", "target": "HBD"}, {"source": "MMRN1", "target": "FGG"}, {"source": "ANK1", "target": "MMRN1"}, {"source": "TUBB1", "target": "PF4"}, {"source": "FGG", "target": "HBD"}, {"source": "PPBP", "target": "ITGB3"}, {"source": "MMRN1", "target": "PF4"}, {"source": "ITGA2B", "target": "HBD"}, {"source": "GP1BA", "target": "ITGB3"}, {"source": "TUBB1", "target": "GP1BB"}, {"source": "MMRN1", "target": "GP1BB"}, {"source": "ANK1", "target": "TUBB1"}, {"source": "FGG", "target": "ITGB3"}, {"source": "PPBP", "target": "FGG"}, {"source": "ITGA2B", "target": "ITGB3"}, {"source": "ANK1", "target": "GP1BA"}, {"source": "PPBP", "target": "GP1BA"}, {"source": "TUBB1", "target": "HBD"}, {"source": "ITGA2B", "target": "FGG"}, {"source": "PF4", "target": "GP1BA"}, {"source": "MMRN1", "target": "HBD"}, {"source": "PPBP", "target": "GP1BB"}, {"source": "TUBB1", "target": "MMRN1"}, {"source": "GP1BA", "target": "GP1BB"}, {"source": "FGG", "target": "GP1BA"}, {"source": "ITGA2B", "target": "GP1BA"}, {"source": "TUBB1", "target": "ITGB3"}, {"source": "MMRN1", "target": "ITGB3"}, {"source": "ITGA2B", "target": "GP1BB"}, {"source": "PF4", "target": "HBD"}, {"source": "GP1BA", "target": "HBD"}, {"source": "ANK1", "target": "PPBP"}, {"source": "ANK1", "target": "ITGB3"}, {"source": "TUBB1", "target": "GP1BA"}, {"source": "HBD", "target": "ITGB3"}, {"source": "MMRN1", "target": "GP1BA"}, {"source": "PF4", "target": "ITGB3"}, {"source": "ITGA2B", "target": "PPBP"}, {"source": "ANK1", "target": "FGG"}, {"source": "ITGA2B", "target": "MMRN1"}, {"source": "ITGA2B", "target": "ANK1"}]}