{"tumor_expression": {"rows": ["Cancer Type", "Fold Change", "p-Value"], "data": [["CCRCC", 0.318411891, 2.99e-30], ["HCC", 0.417740907, 1.47e-42], ["HNSCC", 0.173740574, 2.69e-14], ["LSCC", 0.292822279, 6.76e-31], ["LUAD", 0.251744638, 1.12e-27]]}, "survival": {"rows": ["Cancer Type", "Hazard Ratio", "p-Value"], "data": [["CCRCC", 2.038296928, 0.137143557], ["HCC", 1.471446749, 0.152089354], ["HNSCC", 1.339411578, 0.406424543], ["LSCC", 2.095221091, 0.08458717], ["LUAD", 1.530889056, 0.322462671]]}}