{"tumor_expression": {"rows": ["Cancer Type", "Fold Change", "p-Value"], "data": [["CCRCC", -0.267683511, 1.87e-05], ["HCC", -0.574247572, 4.46e-18], ["HNSCC", -0.556768623, 7.92e-13], ["LSCC", -1.17842373, 3.92e-33], ["LUAD", -0.84524326, 7.38e-31]]}, "survival": {"rows": ["Cancer Type", "Hazard Ratio", "p-Value"], "data": [["CCRCC", 0.804627498, 0.634844036], ["HCC", 0.77417053, 0.340122885], ["HNSCC", 0.910387649, 0.788595108], ["LSCC", 1.457096739, 0.376459794], ["LUAD", 0.681122057, 0.368988048]]}}