{"tumor_expression": {"columns": ["Cancer Cohort", "Fold Change", "<i>p</i>-Value"], "data": [["CCRCC", -1.254004483, 2.28e-28], ["HCC", -0.910592153, 5.36e-42], ["HNSCC", -0.760416414, 8.87e-24], ["LSCC", -0.156058432, 7.64e-11], ["LUAD", 0.111257842, 0.077886248]]}, "survival": {"columns": ["Cancer Cohort", "Hazard Ratio", "<i>p</i>-Value"], "data": [["CCRCC", 1.032230601, 0.943875508], ["HCC", 0.312781368, 3.48e-05], ["HNSCC", 1.227704163, 0.559050099], ["LSCC", 1.066235011, 0.878390145], ["LUAD", 1.307733607, 0.531587701]]}}