{"tumor_expression": {"columns": ["Cancer Cohort", "Fold Change", "<i>p</i>-Value"], "data": [["CCRCC", 0.170359315, 2.54e-19], ["HCC", 0.635548941, 5.43e-54], ["HNSCC", 0.369631634, 1.8e-21], ["LSCC", 0.643186506, 2.51e-35], ["LUAD", 0.366472052, 6.19e-33]]}, "survival": {"columns": ["Cancer Cohort", "Hazard Ratio", "<i>p</i>-Value"], "data": [["CCRCC", 1.480527067, 0.381413444], ["HCC", 2.125953419, 0.005755487], ["HNSCC", 1.764716174, 0.112578475], ["LSCC", 0.500024692, 0.119344935], ["LUAD", 1.139020226, 0.761019743]]}}