{"nodes": [{"name": "TXNDC11", "value": -1.9208187539523751}, {"name": "EDEM2", "value": -6.431798275933005}, {"name": "RAB43", "value": 9.886056647693163}, {"name": "H6PD", "value": -7.318758762624412}, {"name": "CCPG1", "value": 10.537602002101044}, {"name": "TMED3", "value": 53.67778070526608}, {"name": "P4HB", "value": 43.537602002101046}, {"name": "EDEM3", "value": 37.494850021680094}, {"name": "PDIA5", "value": 22.366531544420415}, {"name": "ERP44", "value": 9.0268721464003}, {"name": "HYOU1", "value": 48.20065945054642}, {"name": "DNAJB11", "value": 0.0}, {"name": "DNAJC3", "value": 0.0}, {"name": "PRDX4", "value": 30.795880017344075}, {"name": "TMED9", "value": 52.283996656365204}, {"name": "PLCH1", "value": -0.3979400086720376}, {"name": "TTC17", "value": 30.920818753952375}, {"name": "PDIA3", "value": 40.221848749616356}, {"name": "CALR", "value": 31.136677139879545}, {"name": "ERLEC1", "value": 65.18708664335715}, {"name": "HSP90B1", "value": 37.769551078621724}, {"name": "HSPA5", "value": 67.2518119729938}, {"name": "SIL1", "value": 58.920818753952375}, {"name": "PPIB", "value": 47.11350927482752}, {"name": "PDIA4", "value": 49.95860731484178}, {"name": "UGGT1", "value": 36.19382002601611}, {"name": "GANAB", "value": 0.0}, {"name": "CHID1", "value": -29.72124639904717}, {"name": "RCN1", "value": 62.408935392973504}, {"name": "PDIA6", "value": 43.356547323513816}, {"name": "MESD", "value": 27.013228265733755}, {"name": "SELENOF", "value": 15.823908740944319}, {"name": "NUCB1", "value": 23.06048074738138}, {"name": "TXNDC12", "value": 85.4948500216801}, {"name": "PRKCSH", "value": 45.356547323513816}, {"name": "POGLUT1", "value": 31.4089353929735}, {"name": "SDF4", "value": 18.040958607678906}, {"name": "LRPAP1", "value": 7.0655015487564325}, {"name": "MCFD2", "value": -5.920818753952375}], "edges": [{"source": "ERP44", "target": "DNAJC3"}, {"source": "ERLEC1", "target": "P4HB"}, {"source": "HSPA5", "target": "PPIB"}, {"source": "UGGT1", "target": "PDIA4"}, {"source": "TTC17", "target": "UGGT1"}, {"source": "ERLEC1", "target": "PDIA4"}, {"source": "EDEM3", "target": "HYOU1"}, {"source": "H6PD", "target": "GANAB"}, {"source": "PLCH1", "target": "HSP90B1"}, {"source": "PRKCSH", "target": "MCFD2"}, {"source": "PDIA4", "target": "TMED9"}, {"source": "CALR", "target": "P4HB"}, {"source": "PDIA3", "target": "CALR"}, {"source": "SDF4", "target": "LRPAP1"}, {"source": "HYOU1", "target": "CALR"}, {"source": "TXNDC12", "target": "CALR"}, {"source": "ERP44", "target": "CALR"}, {"source": "DNAJC3", "target": "TMED9"}, {"source": "HYOU1", "target": "PDIA3"}, {"source": "PRDX4", "target": "CHID1"}, {"source": "TXNDC12", "target": "PDIA3"}, {"source": "PDIA5", "target": "HSP90B1"}, {"source": "ERP44", "target": "PDIA3"}, {"source": "PDIA6", "target": "HYOU1"}, {"source": "NUCB1", "target": "LRPAP1"}, {"source": "UGGT1", "target": "SELENOF"}, {"source": "ERLEC1", "target": "SELENOF"}, {"source": "PDIA6", "target": "PPIB"}, {"source": "H6PD", "target": "P4HB"}, {"source": "PLCH1", "target": "HYOU1"}, {"source": "EDEM3", "target": "CALR"}, {"source": "GANAB", "target": "CALR"}, {"source": "SIL1", "target": "PRDX4"}, {"source": "ERP44", "target": "CHID1"}, {"source": "PLCH1", "target": "PPIB"}, {"source": "PDIA5", "target": "DNAJB11"}, {"source": "DNAJB11", "target": "HSP90B1"}, {"source": "DNAJC3", "target": "PDIA4"}, {"source": "HSPA5", "target": "ERLEC1"}, {"source": "PRDX4", "target": "CCPG1"}, {"source": "EDEM3", "target": "PDIA3"}, {"source": "GANAB", "target": "PDIA3"}, {"source": "UGGT1", "target": "POGLUT1"}, {"source": "PRKCSH", "target": "PDIA4"}, {"source": "HSPA5", "target": "PRDX4"}, {"source": "DNAJB11", "target": "PRKCSH"}, {"source": "HSPA5", "target": "SIL1"}, {"source": "PDIA5", "target": "PDIA6"}, {"source": "PDIA5", "target": "HYOU1"}, {"source": "TXNDC11", "target": "P4HB"}, {"source": "GANAB", "target": "CHID1"}, {"source": "HSPA5", "target": "EDEM3"}, {"source": "PDIA5", "target": "PPIB"}, {"source": "PDIA6", "target": "CALR"}, {"source": "DNAJB11", "target": "DNAJC3"}, {"source": "SDF4", "target": "PRKCSH"}, {"source": "DNAJB11", "target": "PDIA6"}, {"source": "PPIB", "target": "CALR"}, {"source": "NUCB1", "target": "HSP90B1"}, {"source": "ERLEC1", "target": "DNAJC3"}, {"source": "PDIA3", "target": "TMED9"}, {"source": "H6PD", "target": "PDIA5"}, {"source": "DNAJB11", "target": "PPIB"}, {"source": "HYOU1", "target": "TMED9"}, {"source": "PDIA6", "target": "PDIA3"}, {"source": "ERP44", "target": "TMED9"}, {"source": "PPIB", "target": "PDIA3"}, {"source": "EDEM3", "target": "TXNDC11"}, {"source": "NUCB1", "target": "PRKCSH"}, {"source": "SIL1", "target": "UGGT1"}, {"source": "TTC17", "target": "DNAJC3"}, {"source": "PDIA4", "target": "HSP90B1"}, {"source": "PDIA5", "target": "CALR"}, {"source": "PPIB", "target": "CHID1"}, {"source": "HSPA5", "target": "RCN1"}, {"source": "UGGT1", "target": "CALR"}, {"source": "PLCH1", "target": "SIL1"}, {"source": "SIL1", "target": "P4HB"}, {"source": "GANAB", "target": "TXNDC12"}, {"source": "DNAJC3", "target": "HSP90B1"}, {"source": "PRDX4", "target": "UGGT1"}, {"source": "SIL1", "target": "PDIA4"}, {"source": "EDEM3", "target": "TMED9"}, {"source": "HSPA5", "target": "UGGT1"}, {"source": "HYOU1", "target": "PDIA4"}, {"source": "NUCB1", "target": "HYOU1"}, {"source": "TXNDC12", "target": "PDIA4"}, {"source": "PLCH1", "target": "EDEM3"}, {"source": "PRKCSH", "target": "POGLUT1"}, {"source": "PRKCSH", "target": "HSP90B1"}, {"source": "NUCB1", "target": "PPIB"}, {"source": "UGGT1", "target": "PDIA3"}, {"source": "PRDX4", "target": "P4HB"}, {"source": "PDIA6", "target": "MCFD2"}, {"source": "MESD", "target": "HSP90B1"}, {"source": "HSPA5", "target": "P4HB"}, {"source": "HSPA5", "target": "PDIA4"}, {"source": "ERLEC1", "target": "CHID1"}, {"source": "PDIA5", "target": "PRDX4"}, {"source": "LRPAP1", "target": "MCFD2"}, {"source": "MESD", "target": "PRKCSH"}, {"source": "PDIA5", "target": "EDEM3"}, {"source": "ERP44", "target": "PLCH1"}, {"source": "PDIA6", "target": "TMED9"}, {"source": "P4HB", "target": "CCPG1"}, {"source": "EDEM2", "target": "EDEM3"}, {"source": "DNAJB11", "target": "SIL1"}, {"source": "PPIB", "target": "TMED9"}, {"source": "PLCH1", "target": "TMED9"}, {"source": "MESD", "target": "PDIA6"}, {"source": "ERLEC1", "target": "CCPG1"}, {"source": "DNAJB11", "target": "EDEM3"}, {"source": "MESD", "target": "PPIB"}, {"source": "PRDX4", "target": "HSP90B1"}, {"source": "GANAB", "target": "PLCH1"}, {"source": "HSP90B1", "target": "PDIA3"}, {"source": "PDIA4", "target": "CHID1"}, {"source": "TXNDC12", "target": "HSP90B1"}, {"source": "HSP90B1", "target": "CHID1"}, {"source": "PLCH1", "target": "PDIA4"}, {"source": "UGGT1", "target": "TMED9"}, {"source": "ERP44", "target": "HSP90B1"}, {"source": "ERLEC1", "target": "TMED9"}, {"source": "PDIA5", "target": "UGGT1"}, {"source": "TXNDC12", "target": "PRKCSH"}, {"source": "ERP44", "target": "PRKCSH"}, {"source": "PRKCSH", "target": "CHID1"}, {"source": "ERP44", "target": "DNAJB11"}, {"source": "PRDX4", "target": "PDIA6"}, {"source": "DNAJB11", "target": "MESD"}, {"source": "CALR", "target": "TMED9"}, {"source": "PDIA5", "target": "P4HB"}, {"source": "PRDX4", "target": "HYOU1"}, {"source": "PRDX4", "target": "PPIB"}, {"source": "EDEM3", "target": "HSP90B1"}, {"source": "GANAB", "target": "HSP90B1"}, {"source": "DNAJB11", "target": "UGGT1"}, {"source": "EDEM2", "target": "P4HB"}, {"source": "PDIA5", "target": "PDIA4"}, {"source": "ERP44", "target": "PDIA6"}, {"source": "TTC17", "target": "GANAB"}, {"source": "ERP44", "target": "HYOU1"}, {"source": "GANAB", "target": "PRKCSH"}, {"source": "ERP44", "target": "PPIB"}, {"source": "HSPA5", "target": "DNAJC3"}, {"source": "SDF4", "target": "NUCB1"}, {"source": "DNAJB11", "target": "PDIA4"}, {"source": "LRPAP1", "target": "SELENOF"}, {"source": "SIL1", "target": "CALR"}, {"source": "HSP90B1", "target": "TMED9"}, {"source": "MESD", "target": "PRDX4"}, {"source": "DNAJC3", "target": "TXNDC12"}, {"source": "SDF4", "target": "P4HB"}, {"source": "EDEM3", "target": "PDIA6"}, {"source": "GANAB", "target": "PDIA6"}, {"source": "PDIA6", "target": "HSP90B1"}, {"source": "PRDX4", "target": "CALR"}, {"source": "SIL1", "target": "PDIA3"}, {"source": "GANAB", "target": "HYOU1"}, {"source": "HSPA5", "target": "CALR"}, {"source": "EDEM3", "target": "PPIB"}, {"source": "TMED3", "target": "P4HB"}, {"source": "PDIA5", "target": "RAB43"}, {"source": "PRDX4", "target": "PDIA3"}, {"source": "NUCB1", "target": "PDIA4"}, {"source": "HSPA5", "target": "PDIA3"}, {"source": "DNAJC3", "target": "MESD"}, {"source": "DNAJC3", "target": "UGGT1"}, {"source": "PDIA4", "target": "P4HB"}, {"source": "UGGT1", "target": "HSP90B1"}, {"source": "ERLEC1", "target": "HSP90B1"}, {"source": "PDIA3", "target": "CCPG1"}, {"source": "HSP90B1", "target": "P4HB"}, {"source": "PRDX4", "target": "TMED3"}, {"source": "PRKCSH", "target": "UGGT1"}, {"source": "DNAJC3", "target": "P4HB"}, {"source": "ERP44", "target": "PRDX4"}, {"source": "ERP44", "target": "SIL1"}, {"source": "MESD", "target": "UGGT1"}, {"source": "ERLEC1", "target": "DNAJB11"}, {"source": "TTC17", "target": "HSP90B1"}, {"source": "PRKCSH", "target": "P4HB"}, {"source": "ERP44", "target": "EDEM3"}, {"source": "DNAJB11", "target": "HYOU1"}, {"source": "SIL1", "target": "TMED9"}, {"source": "UGGT1", "target": "PDIA6"}, {"source": "MESD", "target": "PDIA4"}, {"source": "ERLEC1", "target": "PDIA6"}, {"source": "HSPA5", "target": "TTC17"}, {"source": "UGGT1", "target": "HYOU1"}, {"source": "PLCH1", "target": "PDIA3"}, {"source": "ERLEC1", "target": "HYOU1"}, {"source": "EDEM3", "target": "SIL1"}, {"source": "UGGT1", "target": "PPIB"}, {"source": "ERLEC1", "target": "PPIB"}, {"source": "RCN1", "target": "HSP90B1"}, {"source": "HSPA5", "target": "TXNDC12"}, {"source": "PRDX4", "target": "TMED9"}, {"source": "TMED9", "target": "P4HB"}, {"source": "HSPA5", "target": "TMED9"}, {"source": "HSP90B1", "target": "SELENOF"}, {"source": "EDEM2", "target": "CALR"}, {"source": "TTC17", "target": "HYOU1"}, {"source": "TXNDC12", "target": "MESD"}, {"source": "HSPA5", "target": "GANAB"}, {"source": "PDIA5", "target": "PDIA3"}, {"source": "DNAJB11", "target": "CALR"}, {"source": "EDEM2", "target": "PDIA3"}, {"source": "ERP44", "target": "UGGT1"}, {"source": "RCN1", "target": "PDIA6"}, {"source": "ERP44", "target": "NUCB1"}, {"source": "MESD", "target": "SELENOF"}, {"source": "SIL1", "target": "LRPAP1"}, {"source": "PRDX4", "target": "PDIA4"}, {"source": "RCN1", "target": "HYOU1"}, {"source": "TXNDC12", "target": "LRPAP1"}, {"source": "PDIA3", "target": "P4HB"}, {"source": "SDF4", "target": "CALR"}, {"source": "HYOU1", "target": "P4HB"}, {"source": "DNAJB11", "target": "PDIA3"}, {"source": "ERP44", "target": "P4HB"}, {"source": "PDIA4", "target": "PPIB"}, {"source": "DNAJC3", "target": "PDIA6"}, {"source": "HSP90B1", "target": "PPIB"}, {"source": "ERP44", "target": "PDIA4"}, {"source": "DNAJC3", "target": "HYOU1"}, {"source": "HSPA5", "target": "LRPAP1"}, {"source": "DNAJC3", "target": "PPIB"}, {"source": "PRKCSH", "target": "PDIA6"}, {"source": "EDEM3", "target": "UGGT1"}, {"source": "GANAB", "target": "UGGT1"}, {"source": "PRKCSH", "target": "HYOU1"}, {"source": "NUCB1", "target": "CALR"}, {"source": "HSPA5", "target": "PLCH1"}, {"source": "PRKCSH", "target": "PPIB"}, {"source": "ERP44", "target": "HSPA5"}, {"source": "TMED3", "target": "PDIA3"}, {"source": "ERLEC1", "target": "PRDX4"}, {"source": "EDEM2", "target": "TXNDC11"}, {"source": "GANAB", "target": "P4HB"}, {"source": "EDEM3", "target": "PDIA4"}, {"source": "GANAB", "target": "PDIA4"}, {"source": "NUCB1", "target": "PDIA3"}, {"source": "PDIA4", "target": "CALR"}, {"source": "SIL1", "target": "HSP90B1"}, {"source": "HSP90B1", "target": "CALR"}, {"source": "PDIA5", "target": "TMED9"}, {"source": "HYOU1", "target": "HSP90B1"}, {"source": "TTC17", "target": "SIL1"}, {"source": "DNAJC3", "target": "CALR"}, {"source": "ERP44", "target": "RAB43"}, {"source": "TTC17", "target": "EDEM3"}, {"source": "SELENOF", "target": "P4HB"}, {"source": "PDIA4", "target": "PDIA3"}, {"source": "PRKCSH", "target": "CALR"}, {"source": "PDIA5", "target": "GANAB"}, {"source": "PDIA6", "target": "P4HB"}, {"source": "DNAJB11", "target": "TMED9"}, {"source": "HSPA5", "target": "HSP90B1"}, {"source": "PDIA6", "target": "PDIA4"}, {"source": "HSPA5", "target": "PDIA5"}, {"source": "DNAJC3", "target": "PDIA3"}, {"source": "MESD", "target": "CALR"}, {"source": "PPIB", "target": "P4HB"}, {"source": "RCN1", "target": "SIL1"}, {"source": "PRDX4", "target": "PRKCSH"}, {"source": "SIL1", "target": "PDIA6"}, {"source": "HSPA5", "target": "PRKCSH"}, {"source": "PRKCSH", "target": "PDIA3"}, {"source": "ERLEC1", "target": "MESD"}, {"source": "TXNDC12", "target": "PDIA6"}, {"source": "HSPA5", "target": "DNAJB11"}, {"source": "SIL1", "target": "HYOU1"}, {"source": "SIL1", "target": "PPIB"}, {"source": "DNAJC3", "target": "SIL1"}, {"source": "MESD", "target": "PDIA3"}, {"source": "HYOU1", "target": "PPIB"}, {"source": "TXNDC12", "target": "PPIB"}, {"source": "ERLEC1", "target": "UGGT1"}, {"source": "TMED3", "target": "TMED9"}, {"source": "DNAJC3", "target": "EDEM3"}, {"source": "HSPA5", "target": "PDIA6"}, {"source": "GANAB", "target": "POGLUT1"}, {"source": "HSPA5", "target": "HYOU1"}, {"source": "NUCB1", "target": "TMED9"}, {"source": "UGGT1", "target": "P4HB"}]}