{"nodes": [{"name": "NOP10", "value": 82.55284196865779}, {"name": "DKC1", "value": 97.33724216831843}, {"name": "NKRF", "value": 119.2518119729938}, {"name": "IMP4", "value": 98.33724216831843}, {"name": "RRP15", "value": 143.76955107862173}, {"name": "RRP8", "value": 104.88605664769317}, {"name": "FBL", "value": 124.36653154442041}, {"name": "UTP23", "value": 79.0}, {"name": "FCF1", "value": 78.39794000867204}, {"name": "NOL9", "value": 83.58502665202919}, {"name": "RRP36", "value": 62.82390874094432}, {"name": "REXO4", "value": 139.3187587626244}, {"name": "FAM207A", "value": 84.65757731917779}, {"name": "DDX49", "value": 65.6197887582884}, {"name": "USP36", "value": 95.06048074738138}, {"name": "NOM1", "value": 123.19382002601611}, {"name": "CMSS1", "value": 117.53760200210104}, {"name": "RBM19", "value": 130.52287874528034}, {"name": "UTP25", "value": 135.16115090926274}, {"name": "ABT1", "value": 108.76955107862173}, {"name": "ESF1", "value": 157.06550154875643}, {"name": "WDR3", "value": 80.45593195564973}, {"name": "AATF", "value": 106.30980391997149}, {"name": "RRP7A", "value": 93.82390874094432}, {"name": "NAT10", "value": 0.0}, {"name": "IMP3", "value": 69.52287874528034}, {"name": "NOL10", "value": 143.2441251443275}, {"name": "DDX52", "value": 122.46852108295775}, {"name": "WDR12", "value": 143.72124639904717}, {"name": "NGDN", "value": 117.36653154442041}, {"name": "BMS1", "value": 126.52287874528034}, {"name": "TBL3", "value": 131.3565473235138}, {"name": "UTP15", "value": 144.18708664335713}, {"name": "UTP3", "value": 127.88605664769317}, {"name": "DNTTIP2", "value": 117.05551732784983}, {"name": "MPHOSPH10", "value": 129.88605664769315}, {"name": "NOL6", "value": 131.69897000433602}, {"name": "PDCD11", "value": 151.03151705144606}, {"name": "WDR46", "value": 117.10237290870955}, {"name": "UTP6", "value": 135.2839966563652}, {"name": "NOL11", "value": 149.85387196432177}, {"name": "WDR75", "value": 146.85387196432177}, {"name": "NOL7", "value": 111.48148606012211}, {"name": "DDX47", "value": 131.3279021420643}, {"name": "WDR43", "value": 150.72124639904717}, {"name": "ZCCHC9", "value": 71.13076828026902}], "edges": [{"source": "UTP15", "target": "AATF"}, {"source": "USP36", "target": "DDX47"}, {"source": "FCF1", "target": "DDX52"}, {"source": "CMSS1", "target": "NOL7"}, {"source": "MPHOSPH10", "target": "FAM207A"}, {"source": "ESF1", "target": "BMS1"}, {"source": "WDR75", "target": "CMSS1"}, {"source": "DKC1", "target": "UTP23"}, {"source": "DNTTIP2", "target": "RRP7A"}, {"source": "DDX49", "target": "NOL11"}, {"source": "UTP6", "target": "IMP3"}, {"source": "FCF1", "target": "WDR12"}, {"source": "NGDN", "target": "WDR43"}, {"source": "NOL11", "target": "NOL7"}, {"source": "FBL", "target": "UTP15"}, {"source": "DDX49", "target": "WDR75"}, {"source": "ESF1", "target": "NOL11"}, {"source": "UTP25", "target": "WDR12"}, {"source": "NAT10", "target": "WDR43"}, {"source": "WDR75", "target": "FAM207A"}, {"source": "ESF1", "target": "WDR75"}, {"source": "RBM19", "target": "NKRF"}, {"source": "DNTTIP2", "target": "UTP23"}, {"source": "DNTTIP2", "target": "PDCD11"}, {"source": "RRP36", "target": "UTP3"}, {"source": "NOM1", "target": "RRP7A"}, {"source": "DNTTIP2", "target": "RRP36"}, {"source": "BMS1", "target": "NOP10"}, {"source": "RRP8", "target": "NKRF"}, {"source": "UTP15", "target": "NOP10"}, {"source": "UTP25", "target": "AATF"}, {"source": "MPHOSPH10", "target": "WDR46"}, {"source": "WDR75", "target": "NOM1"}, {"source": "NOL7", "target": "DDX52"}, {"source": "NGDN", "target": "BMS1"}, {"source": "UTP6", "target": "DDX47"}, {"source": "NAT10", "target": "NOL7"}, {"source": "REXO4", "target": "UTP15"}, {"source": "UTP6", "target": "FAM207A"}, {"source": "IMP4", "target": "CMSS1"}, {"source": "WDR3", "target": "DDX49"}, {"source": "WDR43", "target": "IMP3"}, {"source": "TBL3", "target": "NKRF"}, {"source": "WDR75", "target": "WDR46"}, {"source": "WDR12", "target": "TBL3"}, {"source": "IMP3", "target": "DDX52"}, {"source": "PDCD11", "target": "UTP15"}, {"source": "UTP3", "target": "RRP7A"}, {"source": "UTP3", "target": "NOL6"}, {"source": "ZCCHC9", "target": "DDX47"}, {"source": "FBL", "target": "UTP3"}, {"source": "UTP25", "target": "NGDN"}, {"source": "ABT1", "target": "IMP3"}, {"source": "RRP15", "target": "NAT10"}, {"source": "UTP15", "target": "NOL6"}, {"source": "IMP4", "target": "TBL3"}, {"source": "DKC1", "target": "TBL3"}, {"source": "WDR43", "target": "CMSS1"}, {"source": "NOL10", "target": "WDR12"}, {"source": "UTP3", "target": "UTP23"}, {"source": "WDR3", "target": "NOL7"}, {"source": "NOL6", "target": "NKRF"}, {"source": "MPHOSPH10", "target": "UTP15"}, {"source": "IMP4", "target": "NOM1"}, {"source": "ABT1", "target": "CMSS1"}, {"source": "DNTTIP2", "target": "NOL10"}, {"source": "WDR12", "target": "WDR46"}, {"source": "DNTTIP2", "target": "TBL3"}, {"source": "NOL10", "target": "AATF"}, {"source": "RBM19", "target": "IMP4"}, {"source": "WDR3", "target": "NOL11"}, {"source": "DNTTIP2", "target": "ZCCHC9"}, {"source": "UTP23", "target": "AATF"}, {"source": "DDX49", "target": "UTP6"}, {"source": "FCF1", "target": "NOL6"}, {"source": "IMP4", "target": "WDR46"}, {"source": "UTP25", "target": "RRP7A"}, {"source": "WDR3", "target": "WDR75"}, {"source": "UTP25", "target": "NOL6"}, {"source": "ESF1", "target": "UTP6"}, {"source": "NGDN", "target": "NOL9"}, {"source": "RRP8", "target": "IMP4"}, {"source": "BMS1", "target": "IMP3"}, {"source": "NOM1", "target": "TBL3"}, {"source": "FBL", "target": "MPHOSPH10"}, {"source": "UTP25", "target": "ABT1"}, {"source": "CMSS1", "target": "DDX52"}, {"source": "DNTTIP2", "target": "IMP3"}, {"source": "FAM207A", "target": "WDR43"}, {"source": "NOL10", "target": "NGDN"}, {"source": "UTP23", "target": "PDCD11"}, {"source": "ESF1", "target": "WDR12"}, {"source": "WDR43", "target": "WDR46"}, {"source": "MPHOSPH10", "target": "UTP3"}, {"source": "UTP6", "target": "UTP15"}, {"source": "RRP15", "target": "WDR43"}, {"source": "NOL11", "target": "DDX52"}, {"source": "RBM19", "target": "NAT10"}, {"source": "UTP15", "target": "CMSS1"}, {"source": "NGDN", "target": "RRP8"}, {"source": "ABT1", "target": "WDR46"}, {"source": "DDX49", "target": "AATF"}, {"source": "NOM1", "target": "IMP3"}, {"source": "ESF1", "target": "AATF"}, {"source": "NOL9", "target": "RRP7A"}, {"source": "BMS1", "target": "DDX47"}, {"source": "UTP3", "target": "TBL3"}, {"source": "WDR75", "target": "UTP3"}, {"source": "NOL9", "target": "NOL6"}, {"source": "UTP6", "target": "NKRF"}, {"source": "NOL11", "target": "REXO4"}, {"source": "FAM207A", "target": "BMS1"}, {"source": "DNTTIP2", "target": "DDX47"}, {"source": "NOL11", "target": "NOL9"}, {"source": "IMP3", "target": "RRP7A"}, {"source": "RRP15", "target": "BMS1"}, {"source": "NAT10", "target": "DDX52"}, {"source": "DDX49", "target": "PDCD11"}, {"source": "UTP3", "target": "NOM1"}, {"source": "FBL", "target": "FCF1"}, {"source": "NOL10", "target": "RRP7A"}, {"source": "DDX49", "target": "NGDN"}, {"source": "NOL10", "target": "NOL6"}, {"source": "ESF1", "target": "PDCD11"}, {"source": "WDR3", "target": "DKC1"}, {"source": "WDR43", "target": "UTP15"}, {"source": "NAT10", "target": "WDR12"}, {"source": "ESF1", "target": "NGDN"}, {"source": "RRP15", "target": "NOL11"}, {"source": "UTP25", "target": "CMSS1"}, {"source": "NOM1", "target": "DDX47"}, {"source": "FBL", "target": "IMP4"}, {"source": "RRP15", "target": "WDR75"}, {"source": "NOL10", "target": "ABT1"}, {"source": "NOL11", "target": "RRP8"}, {"source": "ABT1", "target": "UTP15"}, {"source": "FBL", "target": "UTP25"}, {"source": "NGDN", "target": "AATF"}, {"source": "UTP15", "target": "WDR46"}, {"source": "FCF1", "target": "TBL3"}, {"source": "UTP25", "target": "TBL3"}, {"source": "WDR3", "target": "DDX52"}, {"source": "RBM19", "target": "WDR43"}, {"source": "WDR75", "target": "MPHOSPH10"}, {"source": "NGDN", "target": "UTP23"}, {"source": "WDR3", "target": "WDR12"}, {"source": "NGDN", "target": "PDCD11"}, {"source": "UTP25", "target": "NOM1"}, {"source": "RRP8", "target": "WDR43"}, {"source": "USP36", "target": "NAT10"}, {"source": "ESF1", "target": "NOL6"}, {"source": "DDX47", "target": "DDX52"}, {"source": "DDX49", "target": "ABT1"}, {"source": "DDX49", "target": "NOL10"}, {"source": "RBM19", "target": "BMS1"}, {"source": "UTP25", "target": "WDR46"}, {"source": "ESF1", "target": "ABT1"}, {"source": "UTP6", "target": "MPHOSPH10"}, {"source": "NOL11", "target": "RRP7A"}, {"source": "FBL", "target": "NOL7"}, {"source": "NOL9", "target": "TBL3"}, {"source": "NOL10", "target": "CMSS1"}, {"source": "DKC1", "target": "NKRF"}, {"source": "REXO4", "target": "WDR43"}, {"source": "RRP8", "target": "BMS1"}, {"source": "RBM19", "target": "NOL11"}, {"source": "RRP36", "target": "WDR43"}, {"source": "MPHOSPH10", "target": "IMP4"}, {"source": "IMP3", "target": "TBL3"}, {"source": "WDR75", "target": "FCF1"}, {"source": "BMS1", "target": "NKRF"}, {"source": "NOL11", "target": "UTP23"}, {"source": "NOL11", "target": "PDCD11"}, {"source": "NOL10", "target": "TBL3"}, {"source": "WDR3", "target": "NGDN"}, {"source": "DNTTIP2", "target": "NKRF"}, {"source": "DDX49", "target": "IMP3"}, {"source": "UTP6", "target": "NAT10"}, {"source": "NOM1", "target": "UTP15"}, {"source": "NAT10", "target": "RRP7A"}, {"source": "REXO4", "target": "NOL7"}, {"source": "NAT10", "target": "NOL6"}, {"source": "WDR75", "target": "IMP4"}, {"source": "RRP15", "target": "UTP6"}, {"source": "NOL9", "target": "WDR46"}, {"source": "WDR75", "target": "UTP25"}, {"source": "NOL10", "target": "NOM1"}, {"source": "RRP36", "target": "BMS1"}, {"source": "PDCD11", "target": "NOL7"}, {"source": "NAT10", "target": "ABT1"}, {"source": "UTP6", "target": "FCF1"}, {"source": "DDX49", "target": "CMSS1"}, {"source": "USP36", "target": "WDR43"}, {"source": "NOL6", "target": "NOL7"}, {"source": "NOM1", "target": "NKRF"}, {"source": "RRP15", "target": "WDR12"}, {"source": "ESF1", "target": "CMSS1"}, {"source": "RRP36", "target": "NOL11"}, {"source": "NOL10", "target": "WDR46"}, {"source": "RRP7A", "target": "NOL7"}, {"source": "DDX49", "target": "DDX47"}, {"source": "UTP23", "target": "WDR46"}, {"source": "FAM207A", "target": "AATF"}, {"source": "DDX49", "target": "FAM207A"}, {"source": "WDR3", "target": "RRP7A"}, {"source": "WDR3", "target": "NOL6"}, {"source": "MPHOSPH10", "target": "NOL7"}, {"source": "RRP15", "target": "AATF"}, {"source": "NGDN", "target": "IMP3"}, {"source": "IMP3", "target": "DDX47"}, {"source": "WDR75", "target": "RBM19"}, {"source": "USP36", "target": "BMS1"}, {"source": "WDR3", "target": "ABT1"}, {"source": "UTP3", "target": "NKRF"}, {"source": "UTP25", "target": "UTP3"}, {"source": "WDR75", "target": "NOL7"}, {"source": "ESF1", "target": "NOM1"}, {"source": "NOL11", "target": "TBL3"}, {"source": "USP36", "target": "NOL11"}, {"source": "UTP6", "target": "WDR43"}, {"source": "NGDN", "target": "CMSS1"}, {"source": "FBL", "target": "DKC1"}, {"source": "RRP15", "target": "PDCD11"}, {"source": "USP36", "target": "WDR75"}, {"source": "WDR3", "target": "RRP36"}, {"source": "NOL11", "target": "ZCCHC9"}, {"source": "RRP15", "target": "NGDN"}, {"source": "DDX49", "target": "WDR46"}, {"source": "NGDN", "target": "DDX47"}, {"source": "ESF1", "target": "WDR46"}, {"source": "UTP23", "target": "UTP15"}, {"source": "RRP15", "target": "NOP10"}, {"source": "ZCCHC9", "target": "WDR43"}, {"source": "NGDN", "target": "FAM207A"}, {"source": "UTP6", "target": "NOL7"}, {"source": "NOL11", "target": "IMP3"}, {"source": "NAT10", "target": "TBL3"}, {"source": "DKC1", "target": "NAT10"}, {"source": "FBL", "target": "DDX52"}, {"source": "DNTTIP2", "target": "FBL"}, {"source": "FAM207A", "target": "NOL6"}, {"source": "UTP6", "target": "NOL11"}, {"source": "NAT10", "target": "NOM1"}, {"source": "CMSS1", "target": "DDX47"}, {"source": "DNTTIP2", "target": "NAT10"}, {"source": "RBM19", "target": "AATF"}, {"source": "UTP6", "target": "WDR75"}, {"source": "RRP15", "target": "NOL6"}, {"source": "DDX49", "target": "UTP15"}, {"source": "NOL10", "target": "UTP3"}, {"source": "REXO4", "target": "DDX52"}, {"source": "NOL11", "target": "DDX47"}, {"source": "ESF1", "target": "UTP15"}, {"source": "RRP8", "target": "AATF"}, {"source": "NAT10", "target": "WDR46"}, {"source": "WDR3", "target": "TBL3"}, {"source": "RRP15", "target": "ABT1"}, {"source": "UTP3", "target": "IMP4"}, {"source": "WDR43", "target": "NOL7"}, {"source": "MPHOSPH10", "target": "DKC1"}, {"source": "PDCD11", "target": "DDX52"}, {"source": "RBM19", "target": "PDCD11"}, {"source": "WDR12", "target": "WDR43"}, {"source": "RBM19", "target": "NGDN"}, {"source": "ABT1", "target": "NOL7"}, {"source": "WDR3", "target": "NOM1"}, {"source": "FBL", "target": "RRP8"}, {"source": "TBL3", "target": "AATF"}, {"source": "RRP8", "target": "PDCD11"}, {"source": "WDR75", "target": "DKC1"}, {"source": "MPHOSPH10", "target": "DDX52"}, {"source": "WDR46", "target": "AATF"}, {"source": "WDR3", "target": "WDR46"}, {"source": "RRP8", "target": "NOP10"}, {"source": "NGDN", "target": "UTP15"}, {"source": "UTP3", "target": "NAT10"}, {"source": "WDR12", "target": "BMS1"}, {"source": "NOL6", "target": "AATF"}, {"source": "ESF1", "target": "UTP3"}, {"source": "DNTTIP2", "target": "DDX49"}, {"source": "MPHOSPH10", "target": "WDR12"}, {"source": "USP36", "target": "WDR12"}, {"source": "DNTTIP2", "target": "WDR43"}, {"source": "UTP25", "target": "IMP4"}, {"source": "MPHOSPH10", "target": "REXO4"}, {"source": "WDR75", "target": "DDX52"}, {"source": "RRP7A", "target": "AATF"}, {"source": "IMP4", "target": "BMS1"}, {"source": "USP36", "target": "RRP15"}, {"source": "RRP15", "target": "CMSS1"}, {"source": "RRP36", "target": "NGDN"}, {"source": "BMS1", "target": "NOL7"}, {"source": "USP36", "target": "AATF"}, {"source": "UTP15", "target": "NOL7"}, {"source": "FBL", "target": "RRP7A"}, {"source": "DKC1", "target": "NOL11"}, {"source": "WDR75", "target": "REXO4"}, {"source": "NOM1", "target": "WDR43"}, {"source": "DNTTIP2", "target": "BMS1"}, {"source": "MPHOSPH10", "target": "RRP8"}, {"source": "FBL", "target": "UTP23"}, {"source": "FBL", "target": "PDCD11"}, {"source": "CMSS1", "target": "NKRF"}, {"source": "USP36", "target": "PDCD11"}, {"source": "DNTTIP2", "target": "NOL11"}, {"source": "UTP6", "target": "WDR12"}, {"source": "RRP15", "target": "NOM1"}, {"source": "USP36", "target": "NGDN"}, {"source": "UTP25", "target": "RBM19"}, {"source": "DDX49", "target": "MPHOSPH10"}, {"source": "REXO4", "target": "NOL6"}, {"source": "DNTTIP2", "target": "WDR75"}, {"source": "IMP4", "target": "DDX52"}, {"source": "ESF1", "target": "MPHOSPH10"}, {"source": "FAM207A", "target": "WDR46"}, {"source": "NOM1", "target": "BMS1"}, {"source": "NOL11", "target": "NKRF"}, {"source": "UTP3", "target": "WDR43"}, {"source": "WDR75", "target": "RRP8"}, {"source": "RBM19", "target": "IMP3"}, {"source": "PDCD11", "target": "RRP7A"}, {"source": "PDCD11", "target": "NOL6"}, {"source": "RRP15", "target": "WDR46"}, {"source": "WDR12", "target": "NOL9"}, {"source": "UTP6", "target": "AATF"}, {"source": "NOL10", "target": "IMP4"}, {"source": "NOL6", "target": "RRP7A"}, {"source": "NKRF", "target": "WDR46"}, {"source": "NOL10", "target": "UTP25"}, {"source": "RRP8", "target": "IMP3"}, {"source": "IMP4", "target": "REXO4"}, {"source": "ESF1", "target": "FBL"}, {"source": "WDR43", "target": "DDX52"}, {"source": "RBM19", "target": "CMSS1"}, {"source": "WDR3", "target": "UTP3"}, {"source": "UTP3", "target": "BMS1"}, {"source": "MPHOSPH10", "target": "RRP7A"}, {"source": "MPHOSPH10", "target": "NOL6"}, {"source": "ABT1", "target": "DDX52"}, {"source": "RBM19", "target": "DDX47"}, {"source": "UTP6", "target": "NGDN"}, {"source": "FAM207A", "target": "UTP15"}, {"source": "USP36", "target": "ABT1"}, {"source": "RRP8", "target": "DDX47"}, {"source": "FBL", "target": "NOL10"}, {"source": "NOL10", "target": "RBM19"}, {"source": "MPHOSPH10", "target": "UTP23"}, {"source": "RRP15", "target": "UTP15"}, {"source": "FBL", "target": "TBL3"}, {"source": "TBL3", "target": "CMSS1"}, {"source": "ESF1", "target": "IMP4"}, {"source": "MPHOSPH10", "target": "RRP36"}, {"source": "ESF1", "target": "UTP25"}, {"source": "WDR3", "target": "NKRF"}, {"source": "NGDN", "target": "NAT10"}, {"source": "UTP23", "target": "NOL7"}, {"source": "WDR75", "target": "UTP23"}, {"source": "WDR75", "target": "PDCD11"}, {"source": "FCF1", "target": "BMS1"}, {"source": "RBM19", "target": "WDR46"}, {"source": "UTP25", "target": "BMS1"}, {"source": "UTP6", "target": "RRP7A"}, {"source": "UTP6", "target": "NOL6"}, {"source": "RRP36", "target": "DDX47"}, {"source": "NOL6", "target": "CMSS1"}, {"source": "DNTTIP2", "target": "UTP6"}, {"source": "WDR75", "target": "RRP36"}, {"source": "REXO4", "target": "TBL3"}, {"source": "FBL", "target": "IMP3"}, {"source": "WDR12", "target": "AATF"}, {"source": "USP36", "target": "IMP3"}, {"source": "UTP15", "target": "DDX52"}, {"source": "FCF1", "target": "NOL11"}, {"source": "NOL9", "target": "WDR43"}, {"source": "UTP6", "target": "ABT1"}, {"source": "DDX49", "target": "RBM19"}, {"source": "PDCD11", "target": "TBL3"}, {"source": "UTP25", "target": "DKC1"}, {"source": "DKC1", "target": "AATF"}, {"source": "ZCCHC9", "target": "NOL6"}, {"source": "DNTTIP2", "target": "WDR12"}, {"source": "RRP15", "target": "UTP3"}, {"source": "NOL6", "target": "TBL3"}, {"source": "UTP3", "target": "NOL9"}, {"source": "ESF1", "target": "RBM19"}, {"source": "USP36", "target": "CMSS1"}, {"source": "NAT10", "target": "IMP4"}, {"source": "WDR12", "target": "UTP23"}, {"source": "WDR12", "target": "PDCD11"}, {"source": "DDX49", "target": "NOL7"}, {"source": "DNTTIP2", "target": "RRP15"}, {"source": "TBL3", "target": "WDR46"}, {"source": "NOL11", "target": "NAT10"}, {"source": "BMS1", "target": "AATF"}, {"source": "ESF1", "target": "NOL7"}, {"source": "FBL", "target": "DDX47"}, {"source": "REXO4", "target": "WDR46"}, {"source": "NOL9", "target": "BMS1"}, {"source": "IMP4", "target": "UTP23"}, {"source": "DNTTIP2", "target": "AATF"}, {"source": "IMP4", "target": "PDCD11"}, {"source": "MPHOSPH10", "target": "TBL3"}, {"source": "RBM19", "target": "UTP15"}, {"source": "DKC1", "target": "PDCD11"}, {"source": "WDR43", "target": "RRP7A"}, {"source": "UTP25", "target": "DDX52"}, {"source": "WDR43", "target": "NOL6"}, {"source": "PDCD11", "target": "WDR46"}, {"source": "MPHOSPH10", "target": "ZCCHC9"}, {"source": "NOL6", "target": "WDR46"}, {"source": "RRP8", "target": "UTP15"}, {"source": "WDR75", "target": "NOL10"}, {"source": "IMP4", "target": "NOP10"}, {"source": "ABT1", "target": "RRP7A"}, {"source": "ABT1", "target": "NOL6"}, {"source": "MPHOSPH10", "target": "NOM1"}, {"source": "DKC1", "target": "NOP10"}, {"source": "NOL10", "target": "BMS1"}, {"source": "WDR75", "target": "TBL3"}, {"source": "WDR3", "target": "IMP4"}, {"source": "NOM1", "target": "AATF"}, {"source": "RRP7A", "target": "WDR46"}, {"source": "DNTTIP2", "target": "NGDN"}, {"source": "UTP6", "target": "CMSS1"}, {"source": "WDR3", "target": "UTP25"}, {"source": "WDR75", "target": "ZCCHC9"}, {"source": "NGDN", "target": "NOL7"}, {"source": "ABT1", "target": "UTP23"}, {"source": "RRP15", "target": "MPHOSPH10"}, {"source": "NOP10", "target": "TBL3"}, {"source": "DNTTIP2", "target": "NOP10"}, {"source": "WDR3", "target": "DNTTIP2"}, {"source": "RRP36", "target": "UTP15"}, {"source": "UTP6", "target": "TBL3"}, {"source": "WDR75", "target": "IMP3"}, {"source": "DKC1", "target": "NOL6"}, {"source": "NGDN", "target": "NOL11"}, {"source": "UTP25", "target": "RRP8"}, {"source": "UTP3", "target": "AATF"}, {"source": "NOL11", "target": "WDR43"}, {"source": "RRP15", "target": "FBL"}, {"source": "MPHOSPH10", "target": "DDX47"}, {"source": "DKC1", "target": "ABT1"}, {"source": "BMS1", "target": "RRP7A"}, {"source": "UTP6", "target": "NOM1"}, {"source": "NOL10", "target": "DDX52"}, {"source": "WDR3", "target": "RBM19"}, {"source": "UTP15", "target": "RRP7A"}, {"source": "UTP23", "target": "DDX52"}, {"source": "DNTTIP2", "target": "NOL6"}, {"source": "UTP3", "target": "PDCD11"}, {"source": "WDR75", "target": "DDX47"}, {"source": "UTP6", "target": "WDR46"}, {"source": "NOL10", "target": "REXO4"}, {"source": "DNTTIP2", "target": "ABT1"}, {"source": "WDR12", "target": "IMP3"}, {"source": "NOL11", "target": "BMS1"}, {"source": "ESF1", "target": "DKC1"}, {"source": "WDR43", "target": "TBL3"}, {"source": "UTP3", "target": "NOP10"}, {"source": "NOM1", "target": "NOL6"}, {"source": "IMP4", "target": "IMP3"}, {"source": "RRP15", "target": "IMP4"}, {"source": "ZCCHC9", "target": "WDR46"}, {"source": "WDR12", "target": "CMSS1"}, {"source": "RRP15", "target": "UTP25"}, {"source": "ABT1", "target": "TBL3"}, {"source": "RBM19", "target": "MPHOSPH10"}, {"source": "DDX49", "target": "DDX52"}, {"source": "ESF1", "target": "DDX52"}, {"source": "NAT10", "target": "BMS1"}, {"source": "NOL10", "target": "RRP8"}, {"source": "WDR12", "target": "DDX47"}, {"source": "DDX49", "target": "WDR12"}, {"source": "ABT1", "target": "NOM1"}, {"source": "FCF1", "target": "PDCD11"}, {"source": "WDR3", "target": "WDR43"}, {"source": "WDR12", "target": "FAM207A"}, {"source": "UTP25", "target": "UTP23"}, {"source": "FCF1", "target": "NGDN"}, {"source": "UTP25", "target": "PDCD11"}, {"source": "USP36", "target": "UTP3"}, {"source": "IMP4", "target": "DDX47"}, {"source": "REXO4", "target": "NKRF"}, {"source": "ESF1", "target": "REXO4"}, {"source": "UTP25", "target": "RRP36"}, {"source": "IMP4", "target": "FAM207A"}, {"source": "ESF1", "target": "NOL9"}, {"source": "NOL7", "target": "AATF"}, {"source": "DNTTIP2", "target": "CMSS1"}, {"source": "UTP3", "target": "ABT1"}, {"source": "RRP15", "target": "RBM19"}, {"source": "PDCD11", "target": "NKRF"}, {"source": "NOL9", "target": "AATF"}, {"source": "FAM207A", "target": "NOL7"}, {"source": "RRP8", "target": "NAT10"}, {"source": "WDR3", "target": "BMS1"}, {"source": "BMS1", "target": "TBL3"}, {"source": "WDR43", "target": "DDX47"}, {"source": "RRP15", "target": "NOL7"}, {"source": "IMP3", "target": "AATF"}, {"source": "NGDN", "target": "DDX52"}, {"source": "UTP15", "target": "TBL3"}, {"source": "DNTTIP2", "target": "FAM207A"}, {"source": "ABT1", "target": "DDX47"}, {"source": "NGDN", "target": "WDR12"}, {"source": "ESF1", "target": "RRP8"}, {"source": "DDX47", "target": "NOL7"}, {"source": "WDR75", "target": "UTP15"}, {"source": "MPHOSPH10", "target": "NKRF"}, {"source": "UTP23", "target": "RRP7A"}, {"source": "UTP23", "target": "NOL6"}, {"source": "NGDN", "target": "REXO4"}, {"source": "UTP6", "target": "UTP3"}, {"source": "DNTTIP2", "target": "NOM1"}, {"source": "UTP3", "target": "IMP3"}, {"source": "NOL9", "target": "NOP10"}, {"source": "UTP15", "target": "IMP3"}, {"source": "NAT10", "target": "NOL9"}, {"source": "USP36", "target": "MPHOSPH10"}, {"source": "NOL10", "target": "UTP23"}, {"source": "NOL10", "target": "PDCD11"}, {"source": "BMS1", "target": "WDR46"}, {"source": "WDR75", "target": "NKRF"}, {"source": "DNTTIP2", "target": "WDR46"}, {"source": "ZCCHC9", "target": "UTP3"}, {"source": "UTP3", "target": "CMSS1"}, {"source": "WDR12", "target": "UTP15"}, {"source": "NOP10", "target": "NKRF"}, {"source": "DDX49", "target": "RRP7A"}, {"source": "DDX49", "target": "NOL6"}, {"source": "NOL11", "target": "WDR12"}, {"source": "UTP3", "target": "FAM207A"}, {"source": "IMP4", "target": "UTP15"}, {"source": "ESF1", "target": "RRP7A"}, {"source": "UTP15", "target": "DDX47"}, {"source": "NOM1", "target": "WDR46"}, {"source": "DKC1", "target": "UTP15"}, {"source": "CMSS1", "target": "AATF"}, {"source": "FCF1", "target": "IMP3"}, {"source": "RBM19", "target": "NOL7"}, {"source": "WDR3", "target": "NOL9"}, {"source": "WDR3", "target": "ESF1"}, {"source": "UTP25", "target": "IMP3"}, {"source": "NOL11", "target": "AATF"}, {"source": "RRP8", "target": "NOL7"}, {"source": "IMP4", "target": "NKRF"}, {"source": "ESF1", "target": "UTP23"}, {"source": "DNTTIP2", "target": "UTP15"}, {"source": "AATF", "target": "DDX52"}, {"source": "ESF1", "target": "RRP36"}, {"source": "RRP15", "target": "DKC1"}, {"source": "USP36", "target": "IMP4"}, {"source": "UTP3", "target": "WDR46"}, {"source": "WDR3", "target": "RRP8"}, {"source": "USP36", "target": "UTP25"}, {"source": "TBL3", "target": "NOL7"}, {"source": "UTP25", "target": "DDX47"}, {"source": "NGDN", "target": "RRP7A"}, {"source": "NGDN", "target": "NOL6"}, {"source": "WDR3", "target": "UTP6"}, {"source": "WDR43", "target": "NKRF"}, {"source": "UTP23", "target": "TBL3"}, {"source": "NAT10", "target": "AATF"}, {"source": "FAM207A", "target": "DDX52"}, {"source": "DKC1", "target": "UTP3"}, {"source": "RRP36", "target": "NOL7"}, {"source": "NGDN", "target": "ABT1"}, {"source": "USP36", "target": "DNTTIP2"}, {"source": "ABT1", "target": "NKRF"}, {"source": "RRP15", "target": "DDX52"}, {"source": "FBL", "target": "WDR43"}, {"source": "MPHOSPH10", "target": "NAT10"}, {"source": "NAT10", "target": "UTP23"}, {"source": "NOL10", "target": "IMP3"}, {"source": "NOL9", "target": "CMSS1"}, {"source": "NAT10", "target": "PDCD11"}, {"source": "DNTTIP2", "target": "UTP3"}, {"source": "WDR3", "target": "RRP15"}, {"source": "RRP15", "target": "REXO4"}, {"source": "FCF1", "target": "WDR46"}, {"source": "UTP6", "target": "IMP4"}, {"source": "IMP3", "target": "CMSS1"}, {"source": "UTP3", "target": "UTP15"}, {"source": "NOL9", "target": "DDX47"}, {"source": "WDR3", "target": "AATF"}, {"source": "RRP15", "target": "ESF1"}, {"source": "DDX49", "target": "TBL3"}, {"source": "UTP6", "target": "UTP25"}, {"source": "ESF1", "target": "NOL10"}, {"source": "NOL11", "target": "NOL6"}, {"source": "WDR75", "target": "NAT10"}, {"source": "USP36", "target": "NOL7"}, {"source": "ESF1", "target": "TBL3"}, {"source": "FBL", "target": "BMS1"}, {"source": "NOL11", "target": "ABT1"}, {"source": "NOL10", "target": "DDX47"}, {"source": "DDX47", "target": "AATF"}, {"source": "PDCD11", "target": "WDR43"}, {"source": "WDR3", "target": "PDCD11"}, {"source": "UTP23", "target": "DDX47"}, {"source": "FBL", "target": "NOL11"}, {"source": "NOL10", "target": "FAM207A"}, {"source": "UTP15", "target": "NKRF"}, {"source": "RRP15", "target": "RRP8"}, {"source": "FBL", "target": "WDR75"}, {"source": "NOL7", "target": "WDR46"}, {"source": "ESF1", "target": "IMP3"}, {"source": "UTP6", "target": "RBM19"}, {"source": "FCF1", "target": "UTP15"}, {"source": "RBM19", "target": "DDX52"}, {"source": "UTP25", "target": "UTP15"}, {"source": "DNTTIP2", "target": "MPHOSPH10"}, {"source": "NGDN", "target": "TBL3"}, {"source": "MPHOSPH10", "target": "WDR43"}, {"source": "IMP3", "target": "WDR46"}, {"source": "PDCD11", "target": "BMS1"}, {"source": "RBM19", "target": "WDR12"}, {"source": "NOL6", "target": "BMS1"}, {"source": "RRP8", "target": "DDX52"}, {"source": "RBM19", "target": "REXO4"}, {"source": "NGDN", "target": "NOM1"}, {"source": "UTP25", "target": "NKRF"}, {"source": "WDR75", "target": "WDR43"}, {"source": "RRP8", "target": "WDR12"}, {"source": "FAM207A", "target": "RRP7A"}, {"source": "ESF1", "target": "DDX47"}, {"source": "ZCCHC9", "target": "NOL7"}, {"source": "NOL11", "target": "CMSS1"}, {"source": "RRP8", "target": "REXO4"}, {"source": "RRP15", "target": "RRP7A"}, {"source": "TBL3", "target": "DDX52"}, {"source": "MPHOSPH10", "target": "BMS1"}, {"source": "NKRF", "target": "AATF"}, {"source": "NGDN", "target": "WDR46"}, {"source": "NAT10", "target": "IMP3"}, {"source": "NOL9", "target": "UTP15"}, {"source": "WDR3", "target": "NOL10"}, {"source": "FCF1", "target": "UTP3"}, {"source": "RRP36", "target": "DDX52"}, {"source": "DNTTIP2", "target": "FCF1"}, {"source": "MPHOSPH10", "target": "NOL11"}, {"source": "NOL11", "target": "FAM207A"}, {"source": "WDR46", "target": "DDX52"}, {"source": "RBM19", "target": "RRP8"}, {"source": "WDR75", "target": "BMS1"}, {"source": "RRP15", "target": "UTP23"}, {"source": "RRP36", "target": "WDR12"}, {"source": "NOL6", "target": "DDX52"}, {"source": "NAT10", "target": "CMSS1"}, {"source": "NOL10", "target": "UTP15"}, {"source": "DNTTIP2", "target": "IMP4"}, {"source": "NOL11", "target": "NOM1"}, {"source": "WDR75", "target": "NOL11"}, {"source": "DNTTIP2", "target": "UTP25"}, {"source": "RRP7A", "target": "DDX52"}, {"source": "CMSS1", "target": "WDR46"}, {"source": "IMP4", "target": "WDR43"}, {"source": "NAT10", "target": "DDX47"}, {"source": "FBL", "target": "UTP6"}, {"source": "WDR3", "target": "IMP3"}, {"source": "PDCD11", "target": "NOL9"}, {"source": "NAT10", "target": "FAM207A"}, {"source": "UTP6", "target": "BMS1"}, {"source": "NOL10", "target": "NKRF"}, {"source": "USP36", "target": "DDX52"}, {"source": "WDR12", "target": "NOL7"}, {"source": "NOL11", "target": "WDR46"}, {"source": "DDX49", "target": "UTP3"}, {"source": "FBL", "target": "WDR12"}, {"source": "IMP4", "target": "NOL7"}, {"source": "WDR3", "target": "CMSS1"}, {"source": "DKC1", "target": "NOL7"}, {"source": "FCF1", "target": "MPHOSPH10"}, {"source": "UTP6", "target": "DKC1"}, {"source": "RBM19", "target": "RRP7A"}, {"source": "RBM19", "target": "NOL6"}, {"source": "MPHOSPH10", "target": "NOL9"}, {"source": "UTP25", "target": "MPHOSPH10"}, {"source": "DNTTIP2", "target": "RBM19"}, {"source": "USP36", "target": "ESF1"}, {"source": "ABT1", "target": "WDR43"}, {"source": "WDR3", "target": "DDX47"}, {"source": "FBL", "target": "AATF"}, {"source": "FAM207A", "target": "TBL3"}, {"source": "RRP8", "target": "RRP7A"}, {"source": "WDR3", "target": "FAM207A"}, {"source": "RRP8", "target": "NOL6"}, {"source": "RBM19", "target": "ABT1"}, {"source": "RRP15", "target": "NOL10"}, {"source": "DNTTIP2", "target": "NOL7"}, {"source": "RBM19", "target": "UTP23"}, {"source": "RRP15", "target": "TBL3"}, {"source": "WDR43", "target": "BMS1"}, {"source": "UTP6", "target": "DDX52"}, {"source": "NOL11", "target": "UTP15"}, {"source": "RRP8", "target": "ABT1"}, {"source": "NGDN", "target": "UTP3"}, {"source": "ESF1", "target": "NKRF"}, {"source": "RBM19", "target": "RRP36"}, {"source": "UTP25", "target": "NAT10"}, {"source": "TBL3", "target": "RRP7A"}, {"source": "ABT1", "target": "BMS1"}, {"source": "FBL", "target": "NGDN"}, {"source": "REXO4", "target": "AATF"}, {"source": "NOM1", "target": "NOL7"}, {"source": "FAM207A", "target": "IMP3"}, {"source": "UTP6", "target": "REXO4"}, {"source": "UTP6", "target": "NOL9"}, {"source": "FBL", "target": "NOP10"}, {"source": "RRP15", "target": "IMP3"}, {"source": "PDCD11", "target": "AATF"}, {"source": "NAT10", "target": "UTP15"}, {"source": "RRP36", "target": "ABT1"}, {"source": "NOL10", "target": "MPHOSPH10"}, {"source": "REXO4", "target": "PDCD11"}, {"source": "DDX47", "target": "WDR46"}, {"source": "NGDN", "target": "NKRF"}, {"source": "UTP3", "target": "NOL7"}, {"source": "NOL11", "target": "UTP3"}, {"source": "UTP6", "target": "RRP8"}, {"source": "WDR75", "target": "WDR12"}, {"source": "MPHOSPH10", "target": "AATF"}, {"source": "USP36", "target": "RRP7A"}, {"source": "FBL", "target": "NOL6"}, {"source": "RRP15", "target": "DDX47"}, {"source": "USP36", "target": "NOL6"}, {"source": "UTP15", "target": "BMS1"}, {"source": "RBM19", "target": "TBL3"}, {"source": "NOL10", "target": "NAT10"}, {"source": "WDR3", "target": "UTP15"}, {"source": "FBL", "target": "ABT1"}, {"source": "NOL6", "target": "NOP10"}, {"source": "UTP25", "target": "WDR43"}, {"source": "WDR75", "target": "AATF"}, {"source": "DDX49", "target": "IMP4"}, {"source": "WDR12", "target": "DDX52"}, {"source": "MPHOSPH10", "target": "PDCD11"}, {"source": "RRP8", "target": "TBL3"}, {"source": "MPHOSPH10", "target": "NGDN"}, {"source": "ABT1", "target": "NOL9"}, {"source": "DDX49", "target": "UTP25"}, {"source": "RBM19", "target": "NOM1"}, {"source": "DNTTIP2", "target": "DKC1"}, {"source": "NOL10", "target": "FCF1"}, {"source": "DKC1", "target": "DDX52"}, {"source": "MPHOSPH10", "target": "NOP10"}, {"source": "WDR12", "target": "REXO4"}, {"source": "UTP25", "target": "NOL7"}, {"source": "WDR75", "target": "NGDN"}, {"source": "IMP4", "target": "WDR12"}, {"source": "BMS1", "target": "DDX52"}, {"source": "RRP36", "target": "TBL3"}, {"source": "DNTTIP2", "target": "DDX52"}, {"source": "RRP8", "target": "WDR46"}, {"source": "DDX49", "target": "NAT10"}, {"source": "UTP25", "target": "NOL11"}, {"source": "ESF1", "target": "NAT10"}, {"source": "IMP4", "target": "AATF"}, {"source": "NGDN", "target": "IMP4"}, {"source": "UTP6", "target": "UTP23"}, {"source": "UTP6", "target": "PDCD11"}, {"source": "FBL", "target": "CMSS1"}, {"source": "DNTTIP2", "target": "REXO4"}, {"source": "NOL10", "target": "WDR43"}, {"source": "UTP6", "target": "RRP36"}, {"source": "DNTTIP2", "target": "NOL9"}, {"source": "REXO4", "target": "IMP3"}, {"source": "NOM1", "target": "DDX52"}, {"source": "DNTTIP2", "target": "ESF1"}, {"source": "MPHOSPH10", "target": "ABT1"}, {"source": "USP36", "target": "NOL10"}, {"source": "DKC1", "target": "RRP8"}, {"source": "WDR75", "target": "RRP7A"}, {"source": "ZCCHC9", "target": "PDCD11"}, {"source": "WDR75", "target": "NOL6"}, {"source": "WDR43", "target": "AATF"}, {"source": "RRP36", "target": "WDR46"}, {"source": "USP36", "target": "TBL3"}, {"source": "IMP3", "target": "NOL7"}, {"source": "PDCD11", "target": "IMP3"}, {"source": "NOL6", "target": "IMP3"}, {"source": "REXO4", "target": "CMSS1"}, {"source": "FAM207A", "target": "NKRF"}, {"source": "NOL10", "target": "NOL7"}, {"source": "ABT1", "target": "AATF"}, {"source": "WDR75", "target": "ABT1"}, {"source": "TBL3", "target": "DDX47"}, {"source": "USP36", "target": "NOM1"}, {"source": "DNTTIP2", "target": "RRP8"}, {"source": "RRP15", "target": "NKRF"}, {"source": "NOL11", "target": "IMP4"}, {"source": "PDCD11", "target": "CMSS1"}, {"source": "UTP23", "target": "BMS1"}, {"source": "UTP3", "target": "DDX52"}, {"source": "REXO4", "target": "DDX47"}, {"source": "WDR3", "target": "MPHOSPH10"}, {"source": "MPHOSPH10", "target": "IMP3"}, {"source": "REXO4", "target": "FAM207A"}, {"source": "DDX49", "target": "WDR43"}, {"source": "NOL10", "target": "NOL11"}, {"source": "WDR12", "target": "RRP7A"}, {"source": "WDR12", "target": "NOL6"}, {"source": "ESF1", "target": "DDX49"}, {"source": "UTP3", "target": "WDR12"}, {"source": "FBL", "target": "WDR46"}, {"source": "PDCD11", "target": "DDX47"}, {"source": "ABT1", "target": "PDCD11"}, {"source": "ESF1", "target": "WDR43"}, {"source": "NOL6", "target": "DDX47"}, {"source": "UTP6", "target": "NOL10"}, {"source": "UTP3", "target": "REXO4"}, {"source": "PDCD11", "target": "FAM207A"}, {"source": "IMP4", "target": "RRP7A"}, {"source": "IMP4", "target": "NOL6"}, {"source": "WDR12", "target": "ABT1"}, {"source": "RBM19", "target": "UTP3"}, {"source": "DKC1", "target": "RRP7A"}, {"source": "MPHOSPH10", "target": "CMSS1"}, {"source": "RRP7A", "target": "DDX47"}, {"source": "WDR3", "target": "FBL"}, {"source": "UTP6", "target": "ZCCHC9"}, {"source": "WDR3", "target": "NAT10"}, {"source": "RRP8", "target": "UTP3"}, {"source": "IMP4", "target": "ABT1"}, {"source": "DDX49", "target": "BMS1"}]}