{"nodes": [{"name": "THOC6", "value": 100.23657200643706}, {"name": "SNRPD1", "value": 74.52287874528034}, {"name": "POLR2E", "value": 96.92081875395237}, {"name": "SNRNP40", "value": 99.39794000867204}, {"name": "SREK1", "value": 99.67778070526609}, {"name": "SRRM2", "value": 89.25963731050575}, {"name": "CPSF3", "value": 128.76955107862173}, {"name": "DDX17", "value": 104.11350927482752}, {"name": "U2AF2", "value": 119.03621217265444}, {"name": "NCL", "value": 118.65757731917779}, {"name": "CWC27", "value": 59.95860731484178}, {"name": "SNRPA1", "value": 110.23657200643706}, {"name": "SF3B6", "value": 109.82390874094432}, {"name": "CPSF2", "value": 91.24412514432751}, {"name": "SF3B5", "value": 78.55284196865779}, {"name": "SNRPF", "value": 56.82390874094432}, {"name": "IWS1", "value": 94.45593195564973}, {"name": "DDX42", "value": 100.3767507096021}, {"name": "SNRPG", "value": 87.92081875395237}, {"name": "PHF5A", "value": 83.46852108295775}, {"name": "XRCC6", "value": 76.72124639904717}, {"name": "SNRPD2", "value": 115.76955107862173}, {"name": "TOP1", "value": 103.82390874094432}, {"name": "NUP50", "value": 98.18708664335715}, {"name": "AKAP8", "value": 80.85387196432177}, {"name": "RAVER1", "value": 28.455931955649724}], "edges": [{"source": "SNRPD2", "target": "CPSF2"}, {"source": "U2AF2", "target": "SNRPA1"}, {"source": "XRCC6", "target": "DDX42"}, {"source": "POLR2E", "target": "RAVER1"}, {"source": "THOC6", "target": "XRCC6"}, {"source": "SNRNP40", "target": "THOC6"}, {"source": "THOC6", "target": "CPSF2"}, {"source": "PHF5A", "target": "AKAP8"}, {"source": "CPSF2", "target": "SF3B5"}, {"source": "PHF5A", "target": "CWC27"}, {"source": "SREK1", "target": "SF3B5"}, {"source": "CPSF3", "target": "SNRPF"}, {"source": "NUP50", "target": "TOP1"}, {"source": "DDX17", "target": "SNRPD2"}, {"source": "SF3B6", "target": "CWC27"}, {"source": "SF3B5", "target": "DDX42"}, {"source": "NCL", "target": "XRCC6"}, {"source": "PHF5A", "target": "SF3B6"}, {"source": "DDX17", "target": "SRRM2"}, {"source": "SNRPA1", "target": "XRCC6"}, {"source": "SNRPD2", "target": "DDX42"}, {"source": "SF3B6", "target": "SF3B5"}, {"source": "POLR2E", "target": "SNRPG"}, {"source": "DDX17", "target": "SREK1"}, {"source": "SNRNP40", "target": "U2AF2"}, {"source": "NCL", "target": "CPSF2"}, {"source": "SNRPD2", "target": "SNRPG"}, {"source": "SNRPA1", "target": "CPSF2"}, {"source": "CWC27", "target": "SREK1"}, {"source": "CPSF3", "target": "SNRPA1"}, {"source": "U2AF2", "target": "XRCC6"}, {"source": "DDX17", "target": "PHF5A"}, {"source": "PHF5A", "target": "SNRPA1"}, {"source": "POLR2E", "target": "TOP1"}, {"source": "SNRPF", "target": "SREK1"}, {"source": "THOC6", "target": "SNRPG"}, {"source": "U2AF2", "target": "CPSF2"}, {"source": "SNRPD2", "target": "CWC27"}, {"source": "CPSF2", "target": "SRRM2"}, {"source": "POLR2E", "target": "SNRPD1"}, {"source": "CPSF3", "target": "SREK1"}, {"source": "SREK1", "target": "IWS1"}, {"source": "SRRM2", "target": "XRCC6"}, {"source": "SREK1", "target": "SRRM2"}, {"source": "NCL", "target": "DDX42"}, {"source": "U2AF2", "target": "RAVER1"}, {"source": "SNRPA1", "target": "DDX42"}, {"source": "SNRPD2", "target": "SF3B5"}, {"source": "PHF5A", "target": "SNRPD2"}, {"source": "U2AF2", "target": "POLR2E"}, {"source": "U2AF2", "target": "CPSF3"}, {"source": "SNRPF", "target": "XRCC6"}, {"source": "SNRNP40", "target": "CWC27"}, {"source": "PHF5A", "target": "IWS1"}, {"source": "SF3B6", "target": "SNRPD2"}, {"source": "PHF5A", "target": "SRRM2"}, {"source": "SF3B6", "target": "IWS1"}, {"source": "AKAP8", "target": "TOP1"}, {"source": "SF3B6", "target": "SRRM2"}, {"source": "SNRNP40", "target": "SF3B6"}, {"source": "NCL", "target": "SNRPG"}, {"source": "SNRPA1", "target": "SNRPG"}, {"source": "SNRNP40", "target": "SNRPF"}, {"source": "SNRNP40", "target": "DDX17"}, {"source": "CPSF3", "target": "XRCC6"}, {"source": "U2AF2", "target": "DDX42"}, {"source": "SNRPF", "target": "CPSF2"}, {"source": "THOC6", "target": "SF3B5"}, {"source": "PHF5A", "target": "XRCC6"}, {"source": "SF3B6", "target": "XRCC6"}, {"source": "U2AF2", "target": "SNRPG"}, {"source": "CPSF3", "target": "CPSF2"}, {"source": "POLR2E", "target": "SNRPA1"}, {"source": "SNRNP40", "target": "SNRPA1"}, {"source": "NUP50", "target": "PHF5A"}, {"source": "SNRPA1", "target": "CWC27"}, {"source": "CWC27", "target": "DDX42"}, {"source": "PHF5A", "target": "CPSF2"}, {"source": "SRRM2", "target": "DDX42"}, {"source": "CPSF3", "target": "RAVER1"}, {"source": "IWS1", "target": "XRCC6"}, {"source": "SF3B6", "target": "CPSF2"}, {"source": "POLR2E", "target": "NCL"}, {"source": "NCL", "target": "SF3B5"}, {"source": "SNRPA1", "target": "SF3B5"}, {"source": "DDX17", "target": "TOP1"}, {"source": "SNRPD2", "target": "IWS1"}, {"source": "SNRPF", "target": "DDX42"}, {"source": "U2AF2", "target": "NUP50"}, {"source": "SNRPD2", "target": "SRRM2"}, {"source": "NUP50", "target": "XRCC6"}, {"source": "U2AF2", "target": "AKAP8"}, {"source": "POLR2E", "target": "SREK1"}, {"source": "IWS1", "target": "CPSF2"}, {"source": "SNRNP40", "target": "SNRPD2"}, {"source": "SNRNP40", "target": "IWS1"}, {"source": "CPSF3", "target": "DDX42"}, {"source": "SNRPD2", "target": "SREK1"}, {"source": "POLR2E", "target": "PHF5A"}, {"source": "U2AF2", "target": "SF3B5"}, {"source": "PHF5A", "target": "DDX42"}, {"source": "DDX17", "target": "CWC27"}, {"source": "AKAP8", "target": "NCL"}, {"source": "DDX17", "target": "SF3B6"}, {"source": "DDX17", "target": "SNRPF"}, {"source": "SNRNP40", "target": "XRCC6"}, {"source": "NUP50", "target": "CPSF3"}, {"source": "PHF5A", "target": "SNRPG"}, {"source": "CWC27", "target": "SF3B5"}, {"source": "SF3B6", "target": "SNRPG"}, {"source": "CPSF2", "target": "TOP1"}, {"source": "IWS1", "target": "DDX42"}, {"source": "NCL", "target": "SNRPD2"}, {"source": "SRRM2", "target": "SF3B5"}, {"source": "NCL", "target": "IWS1"}, {"source": "NCL", "target": "SRRM2"}, {"source": "SNRPA1", "target": "IWS1"}, {"source": "SNRPA1", "target": "SRRM2"}, {"source": "SNRPF", "target": "SF3B5"}, {"source": "SNRNP40", "target": "CPSF2"}, {"source": "POLR2E", "target": "THOC6"}, {"source": "CPSF3", "target": "CWC27"}, {"source": "DDX17", "target": "SNRPA1"}, {"source": "SF3B6", "target": "TOP1"}, {"source": "SNRPD2", "target": "THOC6"}, {"source": "NCL", "target": "SREK1"}, {"source": "SNRNP40", "target": "RAVER1"}, {"source": "SNRPG", "target": "CPSF2"}, {"source": "U2AF2", "target": "SNRPD2"}, {"source": "AKAP8", "target": "XRCC6"}, {"source": "CPSF3", "target": "SF3B5"}, {"source": "POLR2E", "target": "CPSF3"}, {"source": "U2AF2", "target": "IWS1"}, {"source": "SNRNP40", "target": "POLR2E"}, {"source": "U2AF2", "target": "SRRM2"}, {"source": "SNRNP40", "target": "CPSF3"}, {"source": "U2AF2", "target": "NCL"}, {"source": "PHF5A", "target": "SNRPD1"}, {"source": "SF3B6", "target": "SNRPD1"}, {"source": "PHF5A", "target": "SF3B5"}, {"source": "RAVER1", "target": "SRRM2"}, {"source": "POLR2E", "target": "DDX42"}, {"source": "U2AF2", "target": "SREK1"}, {"source": "SNRNP40", "target": "DDX42"}, {"source": "CWC27", "target": "IWS1"}, {"source": "CWC27", "target": "SRRM2"}, {"source": "PHF5A", "target": "SNRPF"}, {"source": "U2AF2", "target": "PHF5A"}, {"source": "AKAP8", "target": "RAVER1"}, {"source": "SF3B6", "target": "SNRPF"}, {"source": "SNRPG", "target": "DDX42"}, {"source": "SNRNP40", "target": "SNRPG"}, {"source": "SNRPF", "target": "IWS1"}, {"source": "NUP50", "target": "DDX17"}, {"source": "SNRPD2", "target": "TOP1"}, {"source": "SNRPF", "target": "SRRM2"}, {"source": "DDX17", "target": "XRCC6"}, {"source": "CWC27", "target": "XRCC6"}, {"source": "CPSF3", "target": "SNRPD2"}, {"source": "AKAP8", "target": "DDX42"}, {"source": "CPSF3", "target": "IWS1"}, {"source": "SF3B6", "target": "SNRPA1"}, {"source": "CPSF3", "target": "SRRM2"}, {"source": "SNRPD2", "target": "SNRPD1"}, {"source": "POLR2E", "target": "CWC27"}, {"source": "THOC6", "target": "TOP1"}, {"source": "DDX17", "target": "CPSF2"}, {"source": "PHF5A", "target": "NCL"}, {"source": "U2AF2", "target": "THOC6"}, {"source": "CWC27", "target": "CPSF2"}, {"source": "POLR2E", "target": "SF3B6"}, {"source": "AKAP8", "target": "SNRPG"}, {"source": "SNRNP40", "target": "SNRPD1"}, {"source": "DDX17", "target": "RAVER1"}, {"source": "POLR2E", "target": "DDX17"}, {"source": "SNRPD2", "target": "SNRPF"}, {"source": "THOC6", "target": "SNRPD1"}, {"source": "PHF5A", "target": "SREK1"}, {"source": "DDX17", "target": "CPSF3"}, {"source": "SF3B6", "target": "SREK1"}, {"source": "SNRPG", "target": "SNRPD1"}, {"source": "IWS1", "target": "SRRM2"}, {"source": "NCL", "target": "TOP1"}, {"source": "NUP50", "target": "SNRPD2"}, {"source": "SNRPA1", "target": "TOP1"}, {"source": "CPSF2", "target": "XRCC6"}, {"source": "NUP50", "target": "SRRM2"}, {"source": "SREK1", "target": "XRCC6"}, {"source": "SNRPD1", "target": "XRCC6"}, {"source": "DDX17", "target": "DDX42"}, {"source": "SNRPD2", "target": "SNRPA1"}, {"source": "NCL", "target": "SNRPD1"}, {"source": "SNRPA1", "target": "SNRPD1"}, {"source": "SREK1", "target": "CPSF2"}, {"source": "DDX17", "target": "SNRPG"}, {"source": "U2AF2", "target": "TOP1"}, {"source": "NCL", "target": "CWC27"}, {"source": "CPSF3", "target": "THOC6"}, {"source": "NCL", "target": "SF3B6"}, {"source": "SREK1", "target": "RAVER1"}, {"source": "THOC6", "target": "SNRPA1"}, {"source": "POLR2E", "target": "SNRPD2"}, {"source": "PHF5A", "target": "THOC6"}, {"source": "NCL", "target": "SNRPF"}, {"source": "POLR2E", "target": "IWS1"}, {"source": "SNRPA1", "target": "SNRPF"}, {"source": "U2AF2", "target": "SNRPD1"}, {"source": "SF3B6", "target": "THOC6"}, {"source": "SNRPF", "target": "SNRPG"}, {"source": "SNRNP40", "target": "SRRM2"}, {"source": "SNRNP40", "target": "NCL"}, {"source": "CWC27", "target": "TOP1"}, {"source": "U2AF2", "target": "CWC27"}, {"source": "SNRPG", "target": "SRRM2"}, {"source": "PHF5A", "target": "CPSF3"}, {"source": "CPSF2", "target": "DDX42"}, {"source": "CPSF3", "target": "SNRPG"}, {"source": "SNRNP40", "target": "SREK1"}, {"source": "SF3B6", "target": "CPSF3"}, {"source": "U2AF2", "target": "SF3B6"}, {"source": "SREK1", "target": "DDX42"}, {"source": "DDX17", "target": "SNRPD1"}, {"source": "POLR2E", "target": "XRCC6"}, {"source": "NCL", "target": "SNRPA1"}, {"source": "U2AF2", "target": "SNRPF"}, {"source": "DDX17", "target": "SF3B5"}, {"source": "CWC27", "target": "SNRPD1"}, {"source": "SF3B5", "target": "XRCC6"}, {"source": "U2AF2", "target": "DDX17"}, {"source": "SNRNP40", "target": "PHF5A"}, {"source": "SNRPD2", "target": "XRCC6"}, {"source": "SNRPG", "target": "SREK1"}, {"source": "AKAP8", "target": "SNRPD2"}, {"source": "SF3B6", "target": "DDX42"}, {"source": "AKAP8", "target": "SRRM2"}, {"source": "SNRPF", "target": "SNRPD1"}, {"source": "POLR2E", "target": "CPSF2"}]}